endex_factset_global_filings/__init__.py
endex_factset_global_filings/_base_client.py
endex_factset_global_filings/_client.py
endex_factset_global_filings/_compat.py
endex_factset_global_filings/_constants.py
endex_factset_global_filings/_exceptions.py
endex_factset_global_filings/_files.py
endex_factset_global_filings/_models.py
endex_factset_global_filings/_qs.py
endex_factset_global_filings/_resource.py
endex_factset_global_filings/_response.py
endex_factset_global_filings/_streaming.py
endex_factset_global_filings/_types.py
endex_factset_global_filings/_version.py
endex_factset_global_filings/py.typed
endex_factset_global_filings/_utils/__init__.py
endex_factset_global_filings/_utils/_logs.py
endex_factset_global_filings/_utils/_proxy.py
endex_factset_global_filings/_utils/_reflection.py
endex_factset_global_filings/_utils/_streams.py
endex_factset_global_filings/_utils/_sync.py
endex_factset_global_filings/_utils/_transform.py
endex_factset_global_filings/_utils/_typing.py
endex_factset_global_filings/_utils/_utils.py
endex_factset_global_filings/lib/.keep
endex_factset_global_filings/resources/__init__.py
endex_factset_global_filings/resources/filings/__init__.py
endex_factset_global_filings/resources/filings/filings.py
endex_factset_global_filings/resources/filings/references/__init__.py
endex_factset_global_filings/resources/filings/references/categories.py
endex_factset_global_filings/resources/filings/references/form_types.py
endex_factset_global_filings/resources/filings/references/references.py
endex_factset_global_filings/resources/filings/references/sources.py
endex_factset_global_filings/resources/filings/references/time_zones.py
endex_factset_global_filings/types/__init__.py
endex_factset_global_filings/types/filing_count_params.py
endex_factset_global_filings/types/filing_count_response.py
endex_factset_global_filings/types/filing_search_params.py
endex_factset_global_filings/types/investment_research.py
endex_factset_global_filings-0.1.0a2.dist-info/METADATA
endex_factset_global_filings-0.1.0a2.dist-info/WHEEL
endex_factset_global_filings-0.1.0a2.dist-info/licenses/LICENSE
endex_factset_global_filings-0.1.0a2.dist-info/RECORD
